[
  {
    "title": "Easy Escape to Andamans ",
    "country": "ANDAMAN & NICOBAR ISLANDS",
    "duration": "3 Nights | 4 Days ",
    "image": "images/destination/destination17.jpg",
    "price": 125,
    "reviews": 209,
    "location": "ANDAMAN & NICOBAR ISLANDS",
    "link": "tour-single.html",
    "plan": "Stay: 02 Nights at Port Blair + 01 Night at Havelock"
  },
  {
    "title": "Best of Havelock & Port Blair",
    "country": "ANDAMAN & NICOBAR ISLANDS",
    "duration": "4 Nights | 5 Days",
    "image": "images/destination/destination15.jpg",
    "price": "21,999",
    "reviews": 170,
    "location": "Greece",
    "link": "tour-single.html",
    "plan": "02 Nights at Port Blair + 02 Nights at Havelock"
  },
  {
    "title": "Explore Andaman",
    "country": "ANDAMAN & NICOBAR ISLANDS",
    "duration": "7 Nights | 8 Days",
    "image": "images/destination/destination17.jpg",
    "price": "39,999",
    "reviews": 230,
    "location": "Croatia",
    "link": "tour-single.html",
    "plan": "03 Nights at Port Blair + 02 Nights at Havelock + 02 Nights at Neil Island"
  },
  {
    "title": "Explore Andaman",
    "country": "ANDAMAN & NICOBAR ISLANDS",
    "duration": "8 Nights | 9 Days",
    "image": "images/destination/destination15.jpg",
    "price": "43,999",
    "reviews": 200,
    "location": "Greece",
    "link": "tour-single.html",
    "plan": "04 Nights at Port Blair + 02 Nights at Havelock + 02 Nights at Neil Island"
  },
  {
    "title": "Explore Andaman",
    "country": "ANDAMAN & NICOBAR ISLANDS",
    "duration": "6 Nights | 7 Days",
    "image": "images/destination/destination17.jpg",
    "price": "29,999",
    "reviews": 223,
    "location": "Croatia",
    "link": "tour-single.html",
    "plan": "03 Nights at Port Blair + 02 Nights at Havelock + 01 Night at Neil Island"
  },
  {
    "title": "Mesmerizing Andamans",
    "country": "ANDAMAN & NICOBAR ISLANDS",
    "duration": "5 Nights | 6 Days",
    "image": "images/destination/destination15.jpg",
    "price": "28,999",
    "reviews": 242,
    "location": "Greece",
    "link": "tour-single.html",
    "plan": "03 Nights at Port Blair + 02 Nights at Havelock"
  },
  {
    "title": "Kerala Tour Package",
    "country": "Kerala",
    "duration": "3 Nights | 4 Days",
    "image": "images/destination/destination17.jpg",
    "price": 125,
    "reviews": 212,
    "location": "Croatia",
    "link": "tour-single.html",
    "plan": "Alleppey (1N) → Munnar (2N) <br> 3–4★ Hotels / Resorts (Generic, as per category)"
  },
  {
    "title": "Athirappilly & Munnar Tour Package",
    "country": "Kerala",
    "duration": "3 Nights | 4 Days",
    "image": "images/destination/destination15.jpg",
    "price": 160,
    "reviews": 198,
    "location": "Greece",
    "link": "tour-single.html",
    "plan": "Athirappilly (1n) » Munnar (2n)"
  },
  {
    "title": "Munnar Tour Package",
    "country": "Kerala",
    "duration": "2 Nights | 3 Days",
    "image": "images/destination/destination17.jpg",
    "price": 125,
    "reviews": 224,
    "location": "Croatia",
    "link": "tour-single.html",
    "plan": "Munnar (2n)"
  },
  {
    "title": "Kerala Tour Package",
    "country": "Kerala",
    "duration": "3 Nights | 4 Days",
    "image": "images/destination/destination15.jpg",
    "price": 160,
    "reviews": 213,
    "location": "Greece",
    "link": "tour-single.html",
    "plan": "Munnar (2N) » Alleppey (1N)"
  },
  {
    "title": "Munnar, Thekkady, Alleppey & Kovalam Tour Package",
    "country": "Kerala",
    "duration": "6 Nights | 7 Days",
    "image": "images/destination/destination17.jpg",
    "price": 125,
    "reviews": 221,
    "location": "Croatia",
    "link": "tour-single.html",
    "plan": "Munnar (2n) » Thekkady (1n) » Alleppey (1n) » Kovalam (2n)"
  },
  {
    "title": "Athirappilly, Munnar, Thekkady & Alleppey Tour Package",
    "country": "Kerala",
    "duration": "5 Nights | 6 Days",
    "image": "images/destination/destination15.jpg",
    "price": 160,
    "reviews": 239,
    "location": "Greece",
    "link": "tour-single.html",
    "plan": "Athirappilly (1n) » Munnar (2n) » Thekkady (1n) » Alleppey (1n)"
  },
  {
    "title": "Munnar, Alleppey & Kovalam Tour Package",
    "country": "Kerala",
    "duration": "5 Nights | 6 Days",
    "image": "images/destination/destination17.jpg",
    "price": 125,
    "reviews": 205,
    "location": "Croatia",
    "link": "tour-single.html",
    "plan": "Munnar (2n) » Alleppey (1n) » Kovalam (2n)"
  },
  {
    "title": "Gujarat Jyotirling Tour Package",
    "country": "Gujarat",
    "duration": "3 Nights | 4 Days",
    "image": "images/destination/destination15.jpg",
    "price": "14,999",
    "reviews": 210,
    "location": "Greece",
    "link": "tour-single.html",
    "plan": "Munnar (2n) » Thekkady (1n) » Alleppey (1n)"
  },
  {
    "title": "Gujarat Jyotirlinga with Statue of Unity Tour Package",
    "country": "Gujarat",
    "duration": "4 Nights | 5 Days",
    "image": "images/destination/destination17.jpg",
    "price": "17,999",
    "reviews": 207,
    "location": "Croatia",
    "link": "tour-single.html",
    "plan": ""
  },
  {
    "title": "Gujarat Darshan with Statue of Unity & Diu Day Excursion Tour Package",
    "country": "Gujarat",
    "duration": "6 Nights | 7 Days",
    "image": "images/destination/destination15.jpg",
    "price": "25,999",
    "reviews": 202,
    "location": "Greece",
    "link": "tour-single.html",
    "plan": ""
  },
  {
    "title": "Gujarat Darshan with Kutch & Statue of Unity Tour Package",
    "country": "Gujarat",
    "duration": "8 Nights | 9 Days",
    "image": "images/destination/destination17.jpg",
    "price": "34,999",
    "reviews": 215,
    "location": "Croatia",
    "link": "tour-single.html",
    "plan": ""
  },
  {
    "title": "Best Ever Temple Tour to Gujarat Tour Package",
    "country": "Gujarat",
    "duration": "6 Nights | 7 Days",
    "image": "images/destination/destination15.jpg",
    "price": "24,999",
    "reviews": 208,
    "location": "Greece",
    "link": "tour-single.html",
    "plan": ""
  },  
  {
    "title": "Gujarat Pilgrimage with Sasan Gir Tour Package",
    "country": "Gujarat",
    "duration": "4 Nights | 5 Days",
    "image": "images/destination/destination17.jpg",
    "price": "17,999",
    "reviews": 220,
    "location": "Croatia",
    "link": "tour-single.html",
    "plan": ""
  },
  {
    "title": " Gujarat Darshan with Gir, Diu & Statue of Unity Tour Package",
    "country": "Gujarat",
    "duration": "6 Nights | 7 Days",
    "image": "images/destination/destination15.jpg",
    "price": "24,999",
    "reviews": 214,
    "location": "Greece",
    "link": "tour-single.html",
    "plan": "Dwarka – Somnath – Sasan Gir – Diu – Vadodara – Statue of Unity – Ahmedabad"
  },
  {
    "title": "Saurashtra Tour Package Tour Package",
    "country": "Gujarat",
    "duration": "6 Nights | 7 Days",
    "image": "images/destination/destination17.jpg",
    "price": "25,999",
    "reviews": 218,
    "location": "Croatia",
    "link": "tour-single.html",
    "plan": "Dwarka (2N) – Somnath (1N) – Diu (1N) – Sasan Gir (1N) – Ahmedabad (1N)"
  },
  {
    "title": "Bhuj – Kutch – Dholavira – Mandvi Tour Package",
    "country": "Gujarat",
    "duration": "4 Nights | 5 Days",
    "image": "images/destination/destination15.jpg",
    "price": "On Request",
    "reviews": 216,
    "location": "Greece",
    "link": "tour-single.html",
    "plan": "Bhuj 3N | Rann of Kutch 1N"
  },
  {
    "title": "Modhera Sun Temple & Statue of Unity Tour Package",
    "country": "Gujarat",
    "duration": "4 Nights | 5 Days",
    "image": "images/destination/destination17.jpg",
    "price": "19,999",
    "reviews": 204,
    "location": "Croatia",
    "link": "tour-single.html",
    "plan": ""
  },
  {
    "title": "Inland Gujarat Jyotirlinga Tour Package",
    "country": "Gujarat",
    "duration": "4 Nights | 5 Days",
    "image": "images/destination/destination15.jpg",
    "price": "17,999",
    "reviews": 211,
    "location": "Greece",
    "link": "tour-single.html",
    "plan": ""
  },
  {
    "title": "Sangam Visit with Chitrakooti Tour Package",
    "country": "Uttar Pradesh",
    "duration": "3 Nights | 4 Days",
    "image": "images/destination/destination17.jpg",
    "price": "17,999",
    "reviews": 226,
    "location": "Croatia",
    "link": "tour-single.html",
    "plan": "Chitrakoot – 2N, Prayagraj – 1N"
  },
  {
    "title": "Divin Kashi Darshan Tour Package",
    "country": "Uttar Pradesh",
    "duration": "2 Nights | 3 Days",
    "image": "images/destination/destination15.jpg",
    "price": "8,999",
    "reviews": 225,
    "location": "Greece",
    "link": "tour-single.html",
    "plan": "Varanasi, Sarnath, Ramnagar Fort, Kashi"
  },
  {
    "title": "Varanasi Special Darshan with Prayagraj & Ayodhya Tour Package",
    "country": "Uttar Pradesh",
    "duration": "4 Nights | 5 Days",
    "image": "images/destination/destination17.jpg",
    "price": "19,999",
    "reviews": 228,
    "location": "Croatia",
    "link": "tour-single.html",
    "plan": "Varanasi – 2N, Prayagraj – 1N, Ayodhya – 1N"
  },
  {
    "title": "Varanasi Special with Vindhyachal Tour Package",
    "country": "Uttar Pradesh",
    "duration": "2 Nights | 3 Days",
    "image": "images/destination/destination15.jpg",
    "price": "11,999",
    "reviews": 231,
    "location": "Greece",
    "link": "tour-single.html",
    "plan": "Varanasi, Sarnath, Ramnagar Fort, Vindhyachal"
  },
  {
    "title": "Varanasi – Prayagraj – Gaya Pilgrimage Tour Package",
    "country": "Uttar Pradesh",
    "duration": "3 Nights | 4 Days",
    "image": "images/destination/destination17.jpg",
    "price": "17,999",
    "reviews": 220,
    "location": "Croatia",
    "link": "tour-single.html",
    "plan": "Varanasi – 2N, Prayagraj – 1D, Bodhgaya – 1N"
  },
  {
    "title": "Varanasi Special with Vindhyachal Tour Package",
    "country": "Uttar Pradesh",
    "duration": "2 Nights | 3 Days",
    "image": "images/destination/destination15.jpg",
    "price": "11,999",
    "reviews": 231,
    "location": "Greece",
    "link": "tour-single.html",
    "plan": "Varanasi, Sarnath, Ramnagar Fort, Vindhyachal"
  },
  {
    "title": "Spiritual Varanasi – Ayodhya – Prayagraj Tour",
    "country": "Uttar Pradesh",
    "duration": "3 Nights | 4 Days",
    "image": "images/destination/destination17.jpg",
    "price": "15,999",
    "reviews": 220,
    "location": "Croatia",
    "link": "tour-single.html",
    "plan": "Varanasi – 2N, Ayodhya – 1N, Prayagraj – 1D"
  },
  {
    "title": "Varanasi – Prayagraj – Gaya Pilgrimage Tour Package",
    "country": "Uttar Pradesh",
    "duration": "3 Nights | 4 Days",
    "image": "images/destination/destination15.jpg",
    "price": "17,999",
    "reviews": 220,
    "location": "Greece",
    "link": "tour-single.html",
    "plan": "Varanasi – 2N, Prayagraj – 1D, Bodhgaya – 1N"
  },
  {
    "title": "Spiritual Varanasi – Ayodhya – Prayagraj Tour",
    "country": "Uttar Pradesh",
    "duration": "3 Nights | 4 Days",
    "image": "images/destination/destination17.jpg",
    "price": "15,999",
    "reviews": 220,
    "location": "Croatia",
    "link": "tour-single.html",
    "plan": "Varanasi – 2N, Ayodhya – 1N, Prayagraj – 1D"
  },
    {
    "title": "Spiritual Varanasi – Ayodhya – Prayagraj Tour",
    "country": "Uttar Pradesh",
    "duration": "3 Nights | 4 Days",
    "image": "images/destination/destination17.jpg",
    "price": "15,999",
    "reviews": 220,
    "location": "Croatia",
    "link": "tour-single.html",
    "plan": "Varanasi – 2N, Ayodhya – 1N, Prayagraj – 1D"
  },
  {
    "title": "Varanasi – Prayagraj – Gaya Pilgrimage Tour Package",
    "country": "Uttar Pradesh",
    "duration": "3 Nights | 4 Days",
    "image": "images/destination/destination15.jpg",
    "price": "17,999",
    "reviews": 220,
    "location": "Greece",
    "link": "tour-single.html",
    "plan": "Varanasi – 2N, Prayagraj – 1D, Bodhgaya – 1N"
  },
  {
    "title": "Spiritual Varanasi – Ayodhya – Prayagraj Tour",
    "country": "Uttar Pradesh",
    "duration": "3 Nights | 4 Days",
    "image": "images/destination/destination17.jpg",
    "price": "15,999",
    "reviews": 220,
    "location": "Croatia",
    "link": "tour-single.html",
    "plan": "Varanasi – 2N, Ayodhya – 1N, Prayagraj – 1D"
  },
  {
    "title": "Meghalaya Tour Package",
    "country": "Meghalaya",
    "duration": "5 Nights | 6 Days",
    "image": "images/destination/destination15.jpg",
    "price": "27,999",
    "reviews": 228,
    "location": "Greece",
    "link": "tour-single.html",
    "plan": "1N Kaziranga + 1N Shillong  + 2N Cherrapunji + 1N Shillong"
  },
  {
    "title": "Meghalaya Tour Package",
    "country": "Meghalaya",
    "duration": "3 Nights | 4 Days",
    "image": "images/destination/destination17.jpg",
    "price": "28,999",
    "reviews": 203,
    "location": "Croatia",
    "link": "tour-single.html",
    "plan": "1N Shillong  + 3N Cherrapunji + 1N Shillong"
  }


 

]